Req_http_vpn/Req_class.py
Req_http_vpn/__init__.py
Req_http_vpn-4.5.0.dist-info/LICENSE
Req_http_vpn-4.5.0.dist-info/METADATA
Req_http_vpn-4.5.0.dist-info/WHEEL
Req_http_vpn-4.5.0.dist-info/top_level.txt
Req_http_vpn-4.5.0.dist-info/RECORD
