Metadata-Version: 2.1
Name: Req-http-vpn
Version: 4.5.0
Summary: A simple and optimized library for sending HTTP requests to closed or filtered sites (:
Home-page: https://github.com/aminrngbr1122
Author: Amin Rngbr
Author-email: rngbramin@gmail.com
License: LICENSE
Keywords: http
License-File: LICENSE
Requires-Dist: colorter
Requires-Dist: requests
